helperize/__init__.py
helperize/cli/__init__.py
helperize/cli/cli.py
helperize/interface.py
helperize/log.py
helperize-0.0.5.dist-info/LICENSE
helperize-0.0.5.dist-info/METADATA
helperize-0.0.5.dist-info/WHEEL
helperize-0.0.5.dist-info/entry_points.txt
helperize-0.0.5.dist-info/RECORD
