Metadata-Version: 2.1
Name: helperize
Version: 0.0.5
Summary: Work with AI helpers that collaborate with you to build practical systems.
License: MIT
Author: Michael Vogelsong
Author-email: 4020875+mjvogelsong@users.noreply.github.com
Requires-Python: >=3.10,<4.0
Classifier: License :: OSI Approved :: MIT License
Classifier: Programming Language :: Python :: 3
Classifier: Programming Language :: Python :: 3.10
Classifier: Programming Language :: Python :: 3.11
Requires-Dist: rich (>=13.3.3,<14.0.0)
Requires-Dist: typer (>=0.7.0,<0.8.0)
